flask_zato.py
Flask_Zato-1.1.2.dist-info/METADATA
Flask_Zato-1.1.2.dist-info/WHEEL
Flask_Zato-1.1.2.dist-info/top_level.txt
Flask_Zato-1.1.2.dist-info/RECORD
