Metadata-Version: 2.1
Name: Flask-Zato
Version: 1.1.2
Summary: Simple Zato integration for Flask
Home-page: UNKNOWN
Author: Michał Węgrzynek
Author-email: mwegrzynek@litexservice.pl
License: BSD
Platform: any
Classifier: Environment :: Web Environment
Classifier: Intended Audience :: Developers
Classifier: License :: OSI Approved :: BSD License
Classifier: Operating System :: OS Independent
Classifier: Programming Language :: Python
Classifier: Topic :: Internet :: WWW/HTTP :: Dynamic Content
Classifier: Topic :: Software Development :: Libraries :: Python Modules
Requires-Dist: Flask
Requires-Dist: requests
